Metadata-Version: 2.1
Name: kinetics-dfba
Version: 0.1.5
Summary: dfba algorithm with kinetics to simulate metabolic activities of microbiota
Home-page: https://gitee.com/Xu_Billy/d-fba-package
Author: Xu Billy
Author-email: xu_tian@stu.scu.edu.cn
License: MIT License
Keywords: dfba with kinetics
Platform: any
